README.rst
setup.py
pipeml/__init__.py
pipeml/_fitted_model.py
pipeml/_multi_predictor.py
pipeml/_normalizer.py
pipeml/_predictor.py
pipeml/_rescaler.py
pipeml.egg-info/PKG-INFO
pipeml.egg-info/SOURCES.txt
pipeml.egg-info/dependency_links.txt
pipeml.egg-info/requires.txt
pipeml.egg-info/top_level.txt