Metadata-Version: 1.2
Name: pipeml
Version: 0.1
Summary: Pipeline tools for machine learning models
Home-page: https://github.com/yoelcortes/pipeml
Author: Yoel Cortes-Pena
Author-email: yoelcortes@gmail.com
License: MIT
Download-URL: https://github.com/yoelcortes/pipeml.git
Keywords: machine learning tools function pipeline
Platform: Windows
Platform: Mac
Platform: Linux
Classifier: Development Status :: 3 - Alpha
Classifier: Environment :: Console
Classifier: License :: OSI Approved :: MIT License
Classifier: Programming Language :: Python :: 3.6
Classifier: Programming Language :: Python :: 3.7
Classifier: Topic :: Scientific/Engineering
Requires-Python: >=3.6
